htm/__init__.py
htm-0.1.1.dist-info/LICENSE
htm-0.1.1.dist-info/METADATA
htm-0.1.1.dist-info/WHEEL
htm-0.1.1.dist-info/top_level.txt
htm-0.1.1.dist-info/RECORD
