Metadata-Version: 2.1
Name: htm
Version: 0.1.1
Summary: HTM for Python
Home-page: https://github.com/jviide/htm.py
Author: Joachim Viide
Author-email: jviide@iki.fi
License: UNKNOWN
Platform: UNKNOWN
Classifier: Programming Language :: Python :: 3
Classifier: License :: OSI Approved :: MIT License
Classifier: Operating System :: OS Independent
Requires-Dist: tagged
Provides-Extra: docs
Requires-Dist: Sphinx ; extra == 'docs'
Requires-Dist: sphinx-rtd-theme ; extra == 'docs'
Requires-Dist: sybil ; extra == 'docs'
Requires-Dist: hyperpython ; extra == 'docs'
